<?xml version="1.0" encoding="UTF-8"?>
<!DOCTYPE tiles-definitions PUBLIC "-//Apache Software Foundation//DTD Tiles Configuration 3.0//EN" "http://tiles.apache.org/dtds/tiles-config_3_0.dtd">

<tiles-definitions>

    <definition name="user/notifications" extends="page-logged">
        <put-attribute name="title" value="Notifications | encuestame" />
        <put-attribute name="menu" expression="/WEB-INF/jsp/includes/menu.jsp" />
        <put-attribute name="content" expression="/WEB-INF/views/notifications/notifications.jsp" />
        <put-attribute name="extra-js" expression="/WEB-INF/views/notifications/js.jsp" />
        <put-attribute name="css_module" expression="/WEB-INF/views/notifications/not_css.jsp" />
        <put-attribute name="dojo-layers" expression="/WEB-INF/views/home/dojo-not.jsp" />
    </definition>

<!--     <definition name="user/notification/id" extends="page">
        <put-attribute name="title" value="Notification Detail | encuestame" />
        <put-attribute name="menu" expression="/WEB-INF/jsp/includes/menu.jsp" />
        <put-attribute name="content" expression="/WEB-INF/views/notifications/notification.jsp" />
        <put-attribute name="extra-js" expression="/WEB-INF/views/notifications/js.jsp" />
    </definition>
 -->

</tiles-definitions>
